{"is_source_file": true, "format": "JavaScript (React JSX)", "description": "This file defines the top-level routing configuration for a Learning Management System (LMS) frontend application using React Router. It sets up various routes for dashboards, course pages, authentication, and public content, with protected routes requiring authentication and roles.", "external_files": ["../auth/ProtectedRoute", "../dashboards/EmployeeDashboard", "../dashboards/AdminDashboard", "../components/LearningPathsList", "../components/CoursesList", "../courses/CoursePlayer", "../auth/SignUpSignIn", "../auth/AdminSignIn", "../pages/CoursesPage", "../pages/AssignmentsPage", "../pages/ProfilePage", "../pages/HealthcheckPage"], "external_methods": ["React", "Routes", "Route", "useParams"], "published": ["AppRoutes"], "classes": [], "methods": [{"name": "AppRoutes", "description": "Main functional component that defines the application's route structure, including protected routes, public routes, and dynamic routes based on URL parameters."}], "calls": ["React", "Routes", "Route", "useParams", "ProtectedRoute", "LearningPathsList", "CoursesList", "CoursePlayer", "SignUpSignIn", "AdminSignIn", "CoursesPage", "AssignmentsPage", "ProfilePage", "HealthcheckPage"], "search-terms": ["React Router", "ProtectedRoute", "Learning Paths", "Courses", "Dashboard", "Healthcheck", "AppRoutes"], "state": 2, "file_id": 25, "knowledge_revision": 192, "git_revision": "0ae87c0fddbc6378335345d02590983864013697", "revision_history": [{"54": ""}, {"72": "6ec14d910a2006ce43e8b03abb7296d232f70a80"}, {"91": "76bf4385bdfaaa3a588b9decebabbb784bde64c0"}, {"96": "e592b744f901e94fffebe0ce23eecafdfc545d28"}, {"98": "e592b744f901e94fffebe0ce23eecafdfc545d28"}, {"108": "f3186e074411647168a00842a8dde2c3c9320580"}, {"125": "9ed779b7f3512e4f3de7693f43897eb8926bb0be"}, {"187": "3b157b2de56565030598e67547a181fcf517a232"}, {"192": "0ae87c0fddbc6378335345d02590983864013697"}], "ctags": [], "filename": "lms_frontend/src/routes/AppRoutes.js", "format-version": 4, "code-base-name": "https://github.com/kavia-common/learning-management-system-257708-257733.git:kavia-main"}